pgml_chat/.gitignore
pgml_chat/main.py
pgml_chat/pgml_playground.py
pgml_chat-0.3.0.dist-info/METADATA
pgml_chat-0.3.0.dist-info/WHEEL
pgml_chat-0.3.0.dist-info/entry_points.txt
pgml_chat-0.3.0.dist-info/RECORD
