Metadata-Version: 2.1
Name: pgml-chat
Version: 0.3.0
Summary: PostgresML bot builder for all your documentation
License: MIT
Author: PostgresML
Author-email: team@postgresml.org
Requires-Python: >=3.8,<4.0
Classifier: License :: OSI Approved :: MIT License
Classifier: Programming Language :: Python :: 3
Classifier: Programming Language :: Python :: 3.8
Classifier: Programming Language :: Python :: 3.9
Classifier: Programming Language :: Python :: 3.10
Classifier: Programming Language :: Python :: 3.11
Requires-Dist: black (>=23.7.0,<24.0.0)
Requires-Dist: click (>=8.1.6,<9.0.0)
Requires-Dist: discord-py (>=2.3.1,<3.0.0)
Requires-Dist: openai (>=1.3.7)
Requires-Dist: pendulum (>=2.1.2,<3.0.0)
Requires-Dist: pgml (>=0.10.0,<0.11.0)
Requires-Dist: python-dotenv (>=1.0.0,<2.0.0)
Requires-Dist: requests (>=2.31.0,<3.0.0)
Requires-Dist: rich (>=13.4.2,<14.0.0)
Requires-Dist: slack-bolt (>=1.18.0,<2.0.0)
